pylivarot.libs/libgsl-619b6bbd.so.19.3.0
pylivarot.libs/libdouble-conversion-f4ece92d.so.1.0
pylivarot.libs/libgslcblas-6e6fdb5d.so.0.0.0
pylivarot-1.0.1.dist-info/METADATA
pylivarot-1.0.1.dist-info/WHEEL
pylivarot-1.0.1.dist-info/top_level.txt
pylivarot-1.0.1.dist-info/LICENSE
pylivarot-1.0.1.dist-info/RECORD
pylivarot/_pylivarot.cpython-37m-x86_64-linux-gnu.so
pylivarot/__init__.py
