Metadata-Version: 2.1
Name: pylivarot
Version: 1.0.1
Summary: Python bindings to Inkscape\'s livarot library
Home-page: https://github.com/CatherineH/livarot_pybind
Author: Catherine Holloway
Author-email: milankie@gmail.com
License: UNKNOWN
Project-URL: Bug Tracker, https://github.com/CatherineH/livarot_pybind/issues
Platform: UNKNOWN
Classifier: Programming Language :: Python :: 3
Classifier: License :: OSI Approved :: GNU General Public License v3 (GPLv3)
Classifier: Operating System :: POSIX :: Linux
License-File: LICENSE
